multi_half_bridge_py.cpython-37m-arm-linux-gnueabihf.so
multi_half_bridge-3.0.0rc0.dist-info/LICENSE.md
multi_half_bridge-3.0.0rc0.dist-info/METADATA
multi_half_bridge-3.0.0rc0.dist-info/WHEEL
multi_half_bridge-3.0.0rc0.dist-info/top_level.txt
multi_half_bridge-3.0.0rc0.dist-info/RECORD
